sqlpipe/SqlPipeBuilder.py
sqlpipe/__init__.py
sqlpipe/__main__.py
sqlpipe-0.2.1.dist-info/LICENSE
sqlpipe-0.2.1.dist-info/METADATA
sqlpipe-0.2.1.dist-info/WHEEL
sqlpipe-0.2.1.dist-info/top_level.txt
sqlpipe-0.2.1.dist-info/RECORD
