Metadata-Version: 2.1
Name: sqlpipe
Version: 0.2.1
Summary: A simple way to run multiple SQL script pipelines in parallel.
Home-page: https://github.com/mariotaddeucci/sqlpipe
Author: Mario Taddeucci
Author-email: mariotaddeucci@gmx.com
License: MIT
Keywords: sql pipeline etl parallel redshift postgres postgresql mysql
Platform: UNKNOWN
Classifier: Programming Language :: Python :: 3
Classifier: License :: OSI Approved :: MIT License
Classifier: Operating System :: OS Independent
Requires-Dist: asyncpg (>=0.21.0)
Requires-Dist: aiomysql (>=0.0.20)
